correly/__init__.py
correly/__main__.py
correly/config.py
correly/models.py
correly/mqtt.py
correly-0.0.1.dist-info/LICENSE
correly-0.0.1.dist-info/METADATA
correly-0.0.1.dist-info/WHEEL
correly-0.0.1.dist-info/entry_points.txt
correly-0.0.1.dist-info/top_level.txt
correly-0.0.1.dist-info/RECORD
